COPYING.txt
HACKING.rst
MANIFEST.in
NEWS.rst
README.rst
setup.py
src/lazr/__init__.py
src/lazr.uri.egg-info/PKG-INFO
src/lazr.uri.egg-info/SOURCES.txt
src/lazr.uri.egg-info/dependency_links.txt
src/lazr.uri.egg-info/namespace_packages.txt
src/lazr.uri.egg-info/not-zip-safe
src/lazr.uri.egg-info/requires.txt
src/lazr.uri.egg-info/top_level.txt
src/lazr/uri/__init__.py
src/lazr/uri/_uri.py
src/lazr/uri/configure.zcml
src/lazr/uri/version.txt
src/lazr/uri/docs/Makefile
src/lazr/uri/docs/NEWS.rst
src/lazr/uri/docs/index.rst
src/lazr/uri/tests/__init__.py
src/lazr/uri/tests/test_docs.py
src/lazr/uri/tests/test_uri.py